LICENSE.txt
README.md
requirements.txt
setup.cfg
setup.py
__tests__/__init__.py
__tests__/dmn_engine_test.py
__tests__/dmn/test.xml
arrow.arrow_dmn.egg-info/PKG-INFO
arrow.arrow_dmn.egg-info/SOURCES.txt
arrow.arrow_dmn.egg-info/dependency_links.txt
arrow.arrow_dmn.egg-info/top_level.txt
arrow_dmn/__init__.py
arrow_dmn/__spi__/__init__.py
arrow_dmn/__spi__/dmn_engine.py
arrow_dmn/__spi__/dmn_process_parser.py
arrow_dmn/__spi__/dmn_process_store.py
arrow_dmn/__spi__/process_ref.py
arrow_dmn/engine/__init__.py
arrow_dmn/engine/sync_dmn_engine.py
arrow_dmn/execution/__init__.py
arrow_dmn/execution/inmemory_business_rule_store.py
arrow_dmn/model/__init__.py
arrow_dmn/model/dmn_decision.py
arrow_dmn/model/dmn_process.py
arrow_dmn/model/dmn_rule.py
arrow_dmn/model/dmn_value.py
arrow_dmn/model/hit_policy.py
arrow_dmn/parser/__init__.py
arrow_dmn/parser/xml_dmn_process_parser.py
arrow_dmn/parser/xml_element.py