Metadata-Version: 2.1
Name: arrow.arrow-dmn
Version: 0.1.1
Summary: DMN runtime designed for the usage in a FaaS environment.
Home-page: https://github.com/c7nw3r/arrow-dmn
Author: x-and-y
Author-email: christian.weber@leftshift.one
License: Apache Software License
Download-URL: https://github.com/c7nw3r/arrow-dmn/archive/refs/tags/v0.1.1.tar.gz
Keywords: dmn-engine
Platform: UNKNOWN
Classifier: Development Status :: 4 - Beta
Classifier: Intended Audience :: Developers
Classifier: License :: OSI Approved :: Apache Software License
Classifier: Programming Language :: Python :: 3
Classifier: Programming Language :: Python :: 3.4
Classifier: Programming Language :: Python :: 3.5
Classifier: Programming Language :: Python :: 3.6
